sigmoid_check/__init__.py
sigmoid_check/excalibur/__init__.py
sigmoid_check/excalibur/numpy_module.py
sigmoid_check/excalibur/pandas_module.py
sigmoid_check/python_odyssey/__init__.py
sigmoid_check/python_odyssey/lesson_10/__init__.py
sigmoid_check/python_odyssey/lesson_10/lesson.py
sigmoid_check/python_odyssey/lesson_11/__init__.py
sigmoid_check/python_odyssey/lesson_11/lesson.py
sigmoid_check/python_odyssey/lesson_13/__init__.py
sigmoid_check/python_odyssey/lesson_13/lesson.py
sigmoid_check/python_odyssey/lesson_14/__init__.py
sigmoid_check/python_odyssey/lesson_14/lesson.py
sigmoid_check/python_odyssey/lesson_15/__init__.py
sigmoid_check/python_odyssey/lesson_15/lesson.py
sigmoid_check/python_odyssey/lesson_16/__init__.py
sigmoid_check/python_odyssey/lesson_16/lesson.py
sigmoid_check/python_warmup/__init__.py
sigmoid_check/python_warmup/python_warmup_checkers.py
sigmoid_check-0.1.5.dist-info/LICENSE
sigmoid_check-0.1.5.dist-info/METADATA
sigmoid_check-0.1.5.dist-info/WHEEL
sigmoid_check-0.1.5.dist-info/top_level.txt
sigmoid_check-0.1.5.dist-info/RECORD
