Metadata-Version: 2.1
Name: sigmoid_check
Version: 0.1.5
Summary: A package for checking the implementation of tasks in Sigmoid Courses
Author: SigmoidAI - Balamatiuc Eduard
Author-email: balamatiuc2@gmail.com
License: Creative Commons Attribution-NonCommercial 4.0 International License
Keywords: tasks,check,sigmoid,sigmoidai,sigmoid_check
Classifier: Development Status :: 3 - Alpha
Classifier: Intended Audience :: Developers
Classifier: License :: OSI Approved :: Apache Software License
Classifier: Programming Language :: Python :: 3
Classifier: Programming Language :: Python :: 3.6
Classifier: Programming Language :: Python :: 3.7
Classifier: Programming Language :: Python :: 3.8
Classifier: Programming Language :: Python :: 3.9
Classifier: Programming Language :: Python :: 3.10
Classifier: Operating System :: OS Independent
License-File: LICENSE
Requires-Dist: numpy >=2.0.0
